Workbook

Sheet Summary
A1: EduSnap Revenue Summary (Freemium: R49/month)
A3: Total revenue, year 1 (R) | B3: ='Monthly Projection'!C16 -> 556493
A4: Total server costs (R) | B4: ='Monthly Projection'!D16 -> 56785
A5: Total hosting (R) | B5: ='Monthly Projection'!F16 -> 1800
A6: Net profit, year 1 (R) | B6: ='Monthly Projection'!G16 -> 497908
A7: Profit margin | B7: =IF(B3=0,0,B6/B3) -> 0.89472464
A8: Mean monthly revenue (R) | B8: =AVERAGE('Monthly Projection'!C4:C15) -> 46374.417
A9: Median monthly revenue (R) | B9: =MEDIAN('Monthly Projection'!C4:C15) -> 42140
A10: Lowest month revenue (R) | B10: =MIN('Monthly Projection'!C4:C15) -> 4900
A11: Highest month revenue (R) | B11: =MAX('Monthly Projection'!C4:C15) -> 98000
A12: Range of monthly revenue (R) | B12: =B11-B10 -> 93100
A13: December monthly revenue (R) | B13: ='Monthly Projection'!C15 -> 98000
A14: Subscriber growth Jan to Dec | B14: ='Monthly Projection'!B15/'Monthly Projection'!B4 -> 20

Sheet Assumptions
A1: EduSnap Revenue Model: Assumptions (Freemium subscription)
A2: Blue = input you can change. Yellow = my assumption, not in your source text. Everything else recalculates.
A4: Input | B4: Value | C4: Source / note
A5: Snap & Learn fee (R per month) | B5: 49 | C5: Your new info: subscriptionFee = R49 (parameter)
A6: Family Plan fee (R per month) | B6: 89 | C6: Your new info: Family Plan R89/month
A7: Share of subscribers on Family Plan | B7: 0 | C7: ASSUMPTION: 0% matches your source maths (all users x R49). Change to model Family sales
A8: Server cost per user (R per month) | B8: 5 | C8: Your new info: serverCostPerUser = R5 (parameter)
A9: Hosting cost (R per month) | B9: 150 | C9: Your new info: Google Sites + AI API free tier, R150/month
A11: Average revenue per subscriber (R) | B11: =B5*(1-B7)+B6*B7 -> 49 | C11: Blended fee given the Family Plan share above
A13: Other notes from your source
A14: Free plan: R0, 5 questions per day (no revenue; not modelled)
A15: Development cost: R0 (student project)
A16: Marketing via schools (no cost given)
A17: Subscribers: Jan 100, Feb 250, Mar 500 and Dec 2,000 are from your source; Apr-Nov are interpolated (see Monthly Projection)

Sheet Monthly Projection
A1: EduSnap 12-Month Revenue Projection (Rand)
A3: Month | B3: Paying subscribers | C3: Revenue (R) | D3: Server costs (R) | E3: Profit before hosting (R) | F3: Hosting (R) | G3: Net profit (R)
A4: Jan | B4: 100 | C4: =B4*Assumptions!$B$11 -> 4900 | D4: =B4*Assumptions!$B$8 -> 500 | E4: =C4-D4 -> 4400 | F4: =Assumptions!$B$9 -> 150 | G4: =E4-F4 -> 4250
A5: Feb | B5: 250 | C5: =B5*Assumptions!$B$11 -> 12250 | D5: =B5*Assumptions!$B$8 -> 1250 | E5: =C5-D5 -> 11000 | F5: =Assumptions!$B$9 -> 150 | G5: =E5-F5 -> 10850
A6: Mar | B6: 500 | C6: =B6*Assumptions!$B$11 -> 24500 | D6: =B6*Assumptions!$B$8 -> 2500 | E6: =C6-D6 -> 22000 | F6: =Assumptions!$B$9 -> 150 | G6: =E6-F6 -> 21850
A7: Apr | B7: =ROUND($B$6*($B$15/$B$6)^((4-3)/9),0) -> 583 | C7: =B7*Assumptions!$B$11 -> 28567 | D7: =B7*Assumptions!$B$8 -> 2915 | E7: =C7-D7 -> 25652 | F7: =Assumptions!$B$9 -> 150 | G7: =E7-F7 -> 25502
A8: May | B8: =ROUND($B$6*($B$15/$B$6)^((5-3)/9),0) -> 680 | C8: =B8*Assumptions!$B$11 -> 33320 | D8: =B8*Assumptions!$B$8 -> 3400 | E8: =C8-D8 -> 29920 | F8: =Assumptions!$B$9 -> 150 | G8: =E8-F8 -> 29770
A9: Jun | B9: =ROUND($B$6*($B$15/$B$6)^((6-3)/9),0) -> 794 | C9: =B9*Assumptions!$B$11 -> 38906 | D9: =B9*Assumptions!$B$8 -> 3970 | E9: =C9-D9 -> 34936 | F9: =Assumptions!$B$9 -> 150 | G9: =E9-F9 -> 34786
A10: Jul | B10: =ROUND($B$6*($B$15/$B$6)^((7-3)/9),0) -> 926 | C10: =B10*Assumptions!$B$11 -> 45374 | D10: =B10*Assumptions!$B$8 -> 4630 | E10: =C10-D10 -> 40744 | F10: =Assumptions!$B$9 -> 150 | G10: =E10-F10 -> 40594
A11: Aug | B11: =ROUND($B$6*($B$15/$B$6)^((8-3)/9),0) -> 1080 | C11: =B11*Assumptions!$B$11 -> 52920 | D11: =B11*Assumptions!$B$8 -> 5400 | E11: =C11-D11 -> 47520 | F11: =Assumptions!$B$9 -> 150 | G11: =E11-F11 -> 47370
A12: Sep | B12: =ROUND($B$6*($B$15/$B$6)^((9-3)/9),0) -> 1260 | C12: =B12*Assumptions!$B$11 -> 61740 | D12: =B12*Assumptions!$B$8 -> 6300 | E12: =C12-D12 -> 55440 | F12: =Assumptions!$B$9 -> 150 | G12: =E12-F12 -> 55290
A13: Oct | B13: =ROUND($B$6*($B$15/$B$6)^((10-3)/9),0) -> 1470 | C13: =B13*Assumptions!$B$11 -> 72030 | D13: =B13*Assumptions!$B$8 -> 7350 | E13: =C13-D13 -> 64680 | F13: =Assumptions!$B$9 -> 150 | G13: =E13-F13 -> 64530
A14: Nov | B14: =ROUND($B$6*($B$15/$B$6)^((11-3)/9),0) -> 1714 | C14: =B14*Assumptions!$B$11 -> 83986 | D14: =B14*Assumptions!$B$8 -> 8570 | E14: =C14-D14 -> 75416 | F14: =Assumptions!$B$9 -> 150 | G14: =E14-F14 -> 75266
A15: Dec | B15: 2000 | C15: =B15*Assumptions!$B$11 -> 98000 | D15: =B15*Assumptions!$B$8 -> 10000 | E15: =C15-D15 -> 88000 | F15: =Assumptions!$B$9 -> 150 | G15: =E15-F15 -> 87850
A16: Year total | C16: =SUM(C4:C15) -> 556493 | D16: =SUM(D4:D15) -> 56785 | E16: =SUM(E4:E15) -> 499708 | F16: =SUM(F4:F15) -> 1800 | G16: =SUM(G4:G15) -> 497908
A18: Yellow subscriber cells (Apr-Nov) are my interpolation: steady growth from 500 in Mar to 2,000 in Dec. Replace with your own figures if you have them.
A19: Profit before hosting reproduces your source figures (Mar: R24,500 revenue, R22,000 profit). Net profit also subtracts the R150 hosting.
